AUTHORS
MANIFEST.in
README.md
setup.py
cfg/twiki.cfg.example
tools/twiki-get-topics
tools/twiki-move-topic
tools/twiki-rename-topic
twiki/__init__.py
twiki/utils.py
twiki.egg-info/PKG-INFO
twiki.egg-info/SOURCES.txt
twiki.egg-info/dependency_links.txt
twiki.egg-info/not-zip-safe
twiki.egg-info/requires.txt
twiki.egg-info/top_level.txt