Metadata-Version: 1.1
Name: twiki
Version: 0.0.3
Summary: A bunch of tools which allow manage a TWiki
Home-page: http://github.com/psaavedra/python-twiki
Author: Pablo Saavedra
Author-email: psaavedra@igalia.com
License: Copyright 2017 Pablo Saavedra <psaavedra@igalia.com>
